{
  "name": "Public Assets",
  "author": "NekoSuneVR",
  "url": "https://vrc-vpm-packages.nekosunevr.co.uk/index.json",
  "id": "co.uk.nekosunevr.listing",
  "packages": {
    "com.i5ucc.vrcaslgestures": {
      "versions": {
        "2.1.1": {
          "name": "com.i5ucc.vrcaslgestures",
          "displayName": "VRC-ASL_Gestures",
          "version": "2.1.1",
          "unity": "2019.4",
          "description": "Gesture AnimationControllers for VRChat 3.0 Avatars to be able to do more ASL Handshapes.",
          "dependencies": {},
          "gitDependencies": {},
          "vpmDependencies": {},
          "legacyFolders": {
            "Assets\\VRC-ASL_Gestures": ""
          },
          "legacyFiles": {},
          "hideInEditor": false,
          "url": "https://github.com/I5UCC/VRC-ASL_Gestures/releases/download/v2.1.1-Hotfix/VRC-ASL_Gestures_v2.1.1-Hotfix_VCC.zip"
        }
      }
    },
    "dev.architech.protv": {
      "versions": {
        "3.0.0-beta.5.1": {
          "name": "dev.architech.protv",
          "displayName": "ArchiTech.ProTV",
          "version": "3.0.0-beta.5.1",
          "unity": "2019.4",
          "description": "A feature-rich, extensible media and video player system for VRChat.",
          "vpmDependencies": {
            "com.vrchat.worlds": "~3.4",
            "dev.architech.sdk": "~0.11"
          },
          "samples": [
            {
              "displayName": "ProTV Showcase Demo",
              "description": "Various pre-made TV setups for different use-cases.",
              "path": "Samples/ProTV Showcase"
            }
          ],
          "author": {
            "name": "ArchiTechVR",
            "email": "archi@techanon.dev"
          },
          "keywords": [
            "protv",
            "udon",
            "video player"
          ],
          "unityRelease": "31f1",
          "zipSHA256": "0830279fa636983f8ffa453a3a039e0e42633bdaae5918d64e1c2e40c509374a",
          "url": "https://gitlab.com/techanon/protv/-/releases/v3.0.0-beta.5.1/downloads/package",
          "legacyFolders": {
            "Assets\\ArchiTechAnon\\ProTV": "62640e80d9f10ee458707b13a97bae04"
          },
          "legacyFiles": {
            "Assets/_pi_/_LTCGI-Adapters/Editor/LTCGI_ProTvAdapterAutoSetup.cs": "",
            "Assets/_pi_/_LTCGI-Adapters/LTCGI_ProTvAdapter.asset": "",
            "Assets/_pi_/_LTCGI-Adapters/LTCGI_ProTvAdapter.cs": "",
            "Assets/_pi_/_LTCGI-Adapters/protv_adapter_version.txt": ""
          }
        },
        "3.0.0-beta.5": {
          "name": "dev.architech.protv",
          "displayName": "ArchiTech.ProTV",
          "version": "3.0.0-beta.5",
          "unity": "2019.4",
          "description": "A feature-rich, extensible media and video player system for VRChat.",
          "vpmDependencies": {
            "com.vrchat.worlds": "~3.4",
            "dev.architech.sdk": "~0.11"
          },
          "samples": [
            {
              "displayName": "ProTV Showcase Demo",
              "description": "Various pre-made TV setups for different use-cases.",
              "path": "Samples/ProTV Showcase"
            }
          ],
          "author": {
            "name": "ArchiTechVR",
            "email": "archi@techanon.dev"
          },
          "keywords": [
            "protv",
            "udon",
            "video player"
          ],
          "unityRelease": "31f1",
          "zipSHA256": "7469eaf2caf18d7ab7231d478df54320fead54975845185e9d151396c37b8e2b",
          "url": "https://gitlab.com/techanon/protv/-/releases/v3.0.0-beta.5/downloads/package",
          "legacyFolders": {
            "Assets\\ArchiTechAnon\\ProTV": "62640e80d9f10ee458707b13a97bae04"
          },
          "legacyFiles": {
            "Assets/_pi_/_LTCGI-Adapters/Editor/LTCGI_ProTvAdapterAutoSetup.cs": "",
            "Assets/_pi_/_LTCGI-Adapters/LTCGI_ProTvAdapter.asset": "",
            "Assets/_pi_/_LTCGI-Adapters/LTCGI_ProTvAdapter.cs": "",
            "Assets/_pi_/_LTCGI-Adapters/protv_adapter_version.txt": ""
          }
        },
        "3.0.0-beta.4": {
          "name": "dev.architech.protv",
          "displayName": "ArchiTech.ProTV",
          "version": "3.0.0-beta.4",
          "unity": "2019.4",
          "description": "A feature-rich, extensible media and video player system for VRChat.",
          "vpmDependencies": {
            "com.vrchat.worlds": ">=3.2.0 <= 3.3.0",
            "com.vrchat.udonsharp": "^1.1.0",
            "dev.architech.sdk": "~0.10"
          },
          "samples": [
            {
              "displayName": "ProTV Showcase Demo",
              "description": "Various pre-made TV setups for different use-cases.",
              "path": "Samples/ProTV Showcase"
            }
          ],
          "author": {
            "name": "ArchiTechVR",
            "email": "archi@techanon.dev"
          },
          "keywords": [
            "protv",
            "udon",
            "video player"
          ],
          "unityRelease": "31f1",
          "zipSHA256": "e2fbabf064a13181c4bb2bf1628000c739e0a48f890238b81e3b4628fb8e1aeb",
          "url": "https://gitlab.com/techanon/protv/-/releases/v3.0.0-beta.4/downloads/package",
          "legacyFolders": {
            "Assets\\ArchiTechAnon\\ProTV": "62640e80d9f10ee458707b13a97bae04"
          },
          "legacyFiles": {
            "Assets/_pi_/_LTCGI-Adapters/Editor/LTCGI_ProTvAdapterAutoSetup.cs": "",
            "Assets/_pi_/_LTCGI-Adapters/LTCGI_ProTvAdapter.asset": "",
            "Assets/_pi_/_LTCGI-Adapters/LTCGI_ProTvAdapter.cs": "",
            "Assets/_pi_/_LTCGI-Adapters/protv_adapter_version.txt": ""
          }
        },
        "3.0.0-beta.3": {
          "name": "dev.architech.protv",
          "displayName": "ArchiTech.ProTV",
          "version": "3.0.0-beta.3",
          "unity": "2019.4",
          "description": "A feature-rich, extensible media and video player system for VRChat.",
          "vpmDependencies": {
            "com.vrchat.worlds": "^3.2.0",
            "com.vrchat.udonsharp": "^1.1.0",
            "dev.architech.sdk": "~0.10.0"
          },
          "samples": [
            {
              "displayName": "ProTV Showcase Demo",
              "description": "Various pre-made TV setups for different use-cases.",
              "path": "Samples/ProTV Showcase"
            }
          ],
          "author": {
            "name": "ArchiTechVR",
            "email": "archi@techanon.dev"
          },
          "keywords": [
            "protv",
            "udon",
            "video player"
          ],
          "unityRelease": "31f1",
          "zipSHA256": "88e5ca89c79f00376147073ee599cc76be583dfc4f590988b192db42873b8667",
          "url": "https://gitlab.com/techanon/protv/-/releases/v3.0.0-beta.3/downloads/package",
          "legacyFolders": {
            "Assets\\ArchiTechAnon\\ProTV": "62640e80d9f10ee458707b13a97bae04"
          },
          "legacyFiles": {
            "Assets/_pi_/_LTCGI-Adapters/Editor/LTCGI_ProTvAdapterAutoSetup.cs": "",
            "Assets/_pi_/_LTCGI-Adapters/LTCGI_ProTvAdapter.asset": "",
            "Assets/_pi_/_LTCGI-Adapters/LTCGI_ProTvAdapter.cs": "",
            "Assets/_pi_/_LTCGI-Adapters/protv_adapter_version.txt": ""
          }
        },
        "3.0.0-beta.2": {
          "name": "dev.architech.protv",
          "displayName": "ArchiTech.ProTV",
          "version": "3.0.0-beta.2",
          "unity": "2019.4",
          "description": "A feature-rich, extensible media and video player system for VRChat.",
          "vpmDependencies": {
            "com.vrchat.worlds": "^3.2.0",
            "com.vrchat.udonsharp": "^1.1.0",
            "dev.architech.sdk": "~0.10.0"
          },
          "samples": [
            {
              "displayName": "ProTV Showcase Demo",
              "description": "Various pre-made TV setups for different use-cases.",
              "path": "Samples/ProTV Showcase"
            }
          ],
          "author": {
            "name": "ArchiTechVR",
            "email": "archi@techanon.dev"
          },
          "keywords": [
            "protv",
            "udon",
            "video player"
          ],
          "unityRelease": "31f1",
          "zipSHA256": "fec2525190ba2ce0e8cc369431c50dea40d7b5f58916f1b0ef370a1f50fa6527",
          "url": "https://gitlab.com/techanon/protv/-/releases/v3.0.0-beta.2/downloads/package",
          "legacyFolders": {
            "Assets\\ArchiTechAnon\\ProTV": "62640e80d9f10ee458707b13a97bae04"
          },
          "legacyFiles": {
            "Assets/_pi_/_LTCGI-Adapters/Editor/LTCGI_ProTvAdapterAutoSetup.cs": "",
            "Assets/_pi_/_LTCGI-Adapters/LTCGI_ProTvAdapter.asset": "",
            "Assets/_pi_/_LTCGI-Adapters/LTCGI_ProTvAdapter.cs": "",
            "Assets/_pi_/_LTCGI-Adapters/protv_adapter_version.txt": ""
          }
        },
        "3.0.0-beta.1": {
          "name": "dev.architech.protv",
          "displayName": "ArchiTech.ProTV",
          "version": "3.0.0-beta.1",
          "unity": "2019.4",
          "description": "A feature-rich, extensible media and video player system for VRChat.",
          "vpmDependencies": {
            "com.vrchat.udonsharp": "^1.1.0",
            "dev.architech.sdk": "~0.10.0"
          },
          "samples": [
            {
              "displayName": "ProTV Showcase Demo",
              "description": "Various pre-made TV setups for different use-cases.",
              "path": "Samples/ProTV Showcase"
            }
          ],
          "author": {
            "name": "ArchiTechVR",
            "email": "archi@techanon.dev"
          },
          "keywords": [
            "protv",
            "udon",
            "video player"
          ],
          "unityRelease": "31f1",
          "zipSHA256": "ceac99bd4b9701d7a1b326c5ee31984c8a34adee977b15068c70ca910653353a",
          "url": "https://gitlab.com/techanon/protv/-/releases/v3.0.0-beta.1/downloads/package",
          "legacyFolders": {
            "Assets\\ArchiTechAnon\\ProTV": "62640e80d9f10ee458707b13a97bae04"
          },
          "legacyFiles": {
            "Assets/_pi_/_LTCGI-Adapters/Editor/LTCGI_ProTvAdapterAutoSetup.cs": "",
            "Assets/_pi_/_LTCGI-Adapters/LTCGI_ProTvAdapter.asset": "",
            "Assets/_pi_/_LTCGI-Adapters/LTCGI_ProTvAdapter.cs": "",
            "Assets/_pi_/_LTCGI-Adapters/protv_adapter_version.txt": ""
          }
        }
      }
    },
    "dev.architech.protv.extras": {
      "versions": {
        "0.5.3-beta": {
          "name": "dev.architech.protv.extras",
          "displayName": "ArchiTech.ProTV.Extras",
          "version": "0.5.3-beta",
          "unity": "2019.4",
          "description": "A community collection of various scripts, prefabs and themes for ProTV.",
          "vpmDependencies": {
            "dev.architech.protv": "^3.0.0-beta.1"
          },
          "samples": [],
          "author": {
            "name": "ArchiTechVR",
            "email": "archi@techanon.dev"
          },
          "keywords": [
            "protv",
            "skins",
            "udon",
            "video player"
          ],
          "unityRelease": "31f1",
          "zipSHA256": "3a20f764efa2e647b18e461b3e48710ef98cd58b7dee1e449ef471b829bf2836",
          "url": "https://gitlab.com/techanon/protv-extras/-/releases/v0.5.3-beta/downloads/package",
          "legacyFolders": {},
          "legacyFiles": {}
        }
      }
    },
    "dev.architech.umbrella": {
      "versions": {
        "0.5.0": {
          "name": "dev.architech.umbrella",
          "displayName": "ArchiTech.Umbrella",
          "version": "0.5.0",
          "unity": "2019.4",
          "description": "A library of gimmicks, mechanics and tools that improves interactivity of worlds.",
          "vpmDependencies": {
            "com.vrchat.worlds": "~3.4",
            "dev.architech.sdk": "~0.11"
          },
          "author": {
            "name": "ArchiTechVR",
            "email": "archi@techanon.dev"
          },
          "unityRelease": "31f1",
          "zipSHA256": "cc267abffbc179eb606794c8a630e7146e750d2dc5d5b8fe3a37b44713c3b9b7",
          "url": "https://gitlab.com/techanon/architech-umbrella/-/releases/v0.5.0/downloads/package"
        },
        "0.4.6": {
          "name": "dev.architech.umbrella",
          "displayName": "ArchiTech.Umbrella",
          "version": "0.4.6",
          "unity": "2019.4",
          "description": "A library of gimmicks, mechanics and tools that improves interactivity of worlds.",
          "vpmDependencies": {
            "com.vrchat.worlds": ">=3.2.0 <= 3.3.0",
            "com.vrchat.udonsharp": "^1.1.0",
            "dev.architech.sdk": "~0.10"
          },
          "author": {
            "name": "ArchiTechVR",
            "email": "archi@techanon.dev"
          },
          "unityRelease": "31f1",
          "zipSHA256": "e27b3eb6030b244d4be15966f648e48019ef1de44379fbfdfceba712bb4ddc79",
          "url": "https://gitlab.com/techanon/architech-umbrella/-/releases/v0.4.6/downloads/package"
        },
        "0.4.5": {
          "name": "dev.architech.umbrella",
          "displayName": "ArchiTech.Umbrella",
          "version": "0.4.5",
          "unity": "2019.4",
          "description": "A library of gimmicks, mechanics and tools that improves interactivity of worlds.",
          "vpmDependencies": {
            "com.vrchat.worlds": ">=3.2.0 <= 3.3.0",
            "com.vrchat.udonsharp": "^1.1.0",
            "dev.architech.sdk": "~0.10"
          },
          "author": {
            "name": "ArchiTechVR",
            "email": "archi@techanon.dev"
          },
          "unityRelease": "31f1",
          "zipSHA256": "fcea1adceddecf67322f70efebd7debf71ad357ba7b0056bf68bd1024a1bbb8f",
          "url": "https://gitlab.com/techanon/architech-umbrella/-/releases/v0.4.5/downloads/package"
        },
        "0.4.4": {
          "name": "dev.architech.umbrella",
          "displayName": "ArchiTech.Umbrella",
          "version": "0.4.4",
          "unity": "2019.4",
          "description": "A library of gimmicks, mechanics and tools that improves interactivity of worlds.",
          "vpmDependencies": {
            "com.vrchat.worlds": "^3.2.0",
            "com.vrchat.udonsharp": "^1.1.0",
            "dev.architech.sdk": "~0.10.0"
          },
          "author": {
            "name": "ArchiTechVR",
            "email": "archi@techanon.dev"
          },
          "unityRelease": "31f1",
          "zipSHA256": "094dfc76616cf2d76a8a02e365242e846771afe0a323e55502e703467150186c",
          "url": "https://gitlab.com/techanon/architech-umbrella/-/releases/v0.4.4/downloads/package"
        },
        "0.4.3": {
          "name": "dev.architech.umbrella",
          "displayName": "ArchiTech.Umbrella",
          "version": "0.4.3",
          "unity": "2019.4",
          "description": "A library of gimmicks, mechanics and tools that improves interactivity of worlds.",
          "vpmDependencies": {
            "com.vrchat.worlds": "^3.2.0",
            "com.vrchat.udonsharp": "^1.1.0",
            "dev.architech.sdk": "~0.10.0"
          },
          "author": {
            "name": "ArchiTechVR",
            "email": "archi@techanon.dev"
          },
          "unityRelease": "31f1",
          "zipSHA256": "ec287d1ca31ba1e0a719a73a8b625b9c06f6a6bc118df0de37ee383ac90df6e1",
          "url": "https://gitlab.com/techanon/architech-umbrella/-/releases/v0.4.3/downloads/package"
        },
        "0.4.2": {
          "name": "dev.architech.umbrella",
          "displayName": "ArchiTech.Umbrella",
          "version": "0.4.2",
          "unity": "2019.4",
          "description": "Library of gimmicks and mechanics that improves interactivity of worlds.",
          "vpmDependencies": {
            "com.vrchat.worlds": "^3.2.0",
            "com.vrchat.udonsharp": "^1.1.0",
            "dev.architech.sdk": "~0.10.0"
          },
          "author": {
            "name": "ArchiTechVR",
            "email": "archi@techanon.dev"
          },
          "unityRelease": "31f1",
          "zipSHA256": "7b576053048c393ea08a6b6b04dc35682d2ed203bc9bf587a8805064f3573655",
          "url": "https://gitlab.com/techanon/architech-umbrella/-/releases/v0.4.2/downloads/package"
        }
      }
    },
    "dev.architech.sdk": {
      "versions": {
        "0.11.0": {
          "name": "dev.architech.sdk",
          "displayName": "ArchiTech.SDK",
          "version": "0.11.0",
          "unity": "2019.4",
          "description": "Library of common functionality used across all of the ArchiTech assets.",
          "vpmDependencies": {
            "com.vrchat.worlds": "~3.4"
          },
          "author": {
            "name": "ArchiTechVR",
            "email": "archi@techanon.dev"
          },
          "unityRelease": "31f1",
          "zipSHA256": "3628e52211d0777f651c4f2f591d9231b16d298fae975d46b152cd4ac05b3f14",
          "url": "https://gitlab.com/techanon/architech-sdk/-/releases/v0.11.0/downloads/package"
        },
        "0.10.2": {
          "name": "dev.architech.sdk",
          "displayName": "ArchiTech.SDK",
          "version": "0.10.2",
          "unity": "2019.4",
          "description": "Library of common functionality used across all of the ArchiTech assets.",
          "vpmDependencies": {
            "com.vrchat.worlds": ">=3.2.0 <= 3.3.0",
            "com.vrchat.udonsharp": "^1.1.0"
          },
          "author": {
            "name": "ArchiTechVR",
            "email": "archi@techanon.dev"
          },
          "unityRelease": "31f1",
          "zipSHA256": "25fe30bad11f36707fb89e1121b0ea941c9b87306d70a733f8399384a27894f7",
          "url": "https://gitlab.com/techanon/architech-sdk/-/releases/v0.10.2/downloads/package"
        },
        "0.10.1": {
          "name": "dev.architech.sdk",
          "displayName": "ArchiTech.SDK",
          "version": "0.10.1",
          "unity": "2019.4",
          "description": "Library of common functionality used across all of the ArchiTech assets.",
          "vpmDependencies": {
            "com.vrchat.worlds": "^3.2.0",
            "com.vrchat.udonsharp": "^1.1.0"
          },
          "author": {
            "name": "ArchiTechVR",
            "email": "archi@techanon.dev"
          },
          "unityRelease": "31f1",
          "zipSHA256": "912553cc86f63b4d8fb81d9ea1075928f105fe5ee07c11254e4333608a93c87d",
          "url": "https://gitlab.com/techanon/architech-sdk/-/releases/v0.10.1/downloads/package"
        },
        "0.10.0": {
          "name": "dev.architech.sdk",
          "displayName": "ArchiTech.SDK",
          "version": "0.10.0",
          "unity": "2019.4",
          "description": "Library of common functionality used across all of the ArchiTech assets.",
          "vpmDependencies": {
            "com.vrchat.udonsharp": "^1.1.0"
          },
          "author": {
            "name": "ArchiTechVR",
            "email": "archi@techanon.dev"
          },
          "unityRelease": "31f1",
          "zipSHA256": "80b0709fe399617b0ece057966569ebac37fee3e98e95fae4f63b3704268eddf",
          "url": "https://gitlab.com/techanon/architech-sdk/-/releases/v0.10.0/downloads/package"
        }
      }
    },
    "io.github.rurre.pumkinsavatartools": {
      "versions": {
        "1.3.9": {
          "name": "io.github.rurre.pumkinsavatartools",
          "displayName": "Pumkins Avatar Tools",
          "version": "1.3.9",
          "unity": "2019.4",
          "description": "An editor script that adds tools to help you setup avatars faster and easier. It includes a component copier that makes it a lot easier to reimport your avatars, and tools to make your thumbnails nicer.",
          "gitDependencies": {},
          "vpmDependencies": {},
          "author": {
            "name": "Pumkin"
          },
          "hideInEditor": false,
          "license": "MIT",
          "zipSHA256": "32895dbae99f731f20935a3fdc468025fc318299232fc2b49bf6fc0c0b1779e0",
          "url": "https://github.com/rurre/PumkinsAvatarTools/releases/download/1.3.9/io.github.rurre.pumkinsavatartools-1.3.9.zip",
          "legacyFolders": {},
          "legacyFiles": {},
          "localPath": ".\\Packages\\io.github.rurre.pumkinsavatartools"
        },
        "1.3.8": {
          "name": "io.github.rurre.pumkinsavatartools",
          "displayName": "Pumkins Avatar Tools",
          "version": "1.3.8",
          "unity": "2019.4",
          "description": "An editor script that adds tools to help you setup avatars faster and easier. It includes a component copier that makes it a lot easier to reimport your avatars, and tools to make your thumbnails nicer.",
          "gitDependencies": {},
          "vpmDependencies": {},
          "author": {
            "name": "Pumkin"
          },
          "hideInEditor": false,
          "license": "MIT",
          "zipSHA256": "32303a89a196e00f267fd552328dd9d6198d129ffff2041c3d74a864a36706fa",
          "url": "https://github.com/rurre/PumkinsAvatarTools/releases/download/1.3.8/io.github.rurre.pumkinsavatartools-1.3.8.zip",
          "legacyFolders": {},
          "legacyFiles": {},
          "localPath": ".\\Packages\\io.github.rurre.pumkinsavatartools"
        },
        "1.3.7": {
          "name": "io.github.rurre.pumkinsavatartools",
          "displayName": "Pumkins Avatar Tools",
          "version": "1.3.7",
          "description": "An editor script that adds tools to help you setup avatars faster and easier. It includes a component copier that makes it a lot easier to reimport your avatars, and tools to make your thumbnails nicer.",
          "gitDependencies": {},
          "vpmDependencies": {},
          "zipSHA256": "1db0b1d46581373ca23649aeca4838b295b14b3f7db725905136987032a07af3",
          "url": "https://github.com/rurre/PumkinsAvatarTools/releases/download/1.3.7/io.github.rurre.pumkinsavatartools-1.3.7.zip",
          "legacyFolders": {},
          "legacyFiles": {},
          "localPath": ".\\Packages\\io.github.rurre.pumkinsavatartools"
        }
      }
    },
    "io.github.rurre.editor-screenshot": {
      "versions": {
        "1.1.2": {
          "name": "io.github.rurre.editor-screenshot",
          "displayName": "Editor Screenshot",
          "version": "1.1.2",
          "unity": "2019.4",
          "description": "An editor tool for taking transparent screenshots in the editor.",
          "gitDependencies": {},
          "vpmDependencies": {},
          "author": {
            "name": "Pumkin"
          },
          "hideInEditor": false,
          "license": "MIT",
          "zipSHA256": "eca2b31e4752db896869355d118197e7be80927195502292f0a33767e9ba4dfc",
          "url": "https://github.com/rurre/Editor-Screenshot/releases/download/1.1.2/io.github.rurre.editor-screenshot-1.1.2.zip",
          "legacyFolders": {},
          "legacyFiles": {},
          "localPath": ".\\Packages\\io.github.rurre.editor-screenshot"
        }
      }
    }
  }
}